booleanOperations/__init__.py
booleanOperations/booleanGlyph.py
booleanOperations/booleanOperationManager.py
booleanOperations/exceptions.py
booleanOperations/flatten.py
booleanOperations/version.py
booleanOperations-0.8.1.dist-info/LICENSE
booleanOperations-0.8.1.dist-info/METADATA
booleanOperations-0.8.1.dist-info/WHEEL
booleanOperations-0.8.1.dist-info/top_level.txt
booleanOperations-0.8.1.dist-info/RECORD
