Metadata-Version: 2.1
Name: booleanOperations
Version: 0.8.1
Summary: Boolean operations on paths.
Home-page: https://github.com/typemytype/booleanOperations
Author: Frederik Berlaen
Author-email: frederik@typemytype.com
License: MIT
Platform: UNKNOWN
Classifier: Development Status :: 4 - Beta
Classifier: Intended Audience :: Developers
Classifier: License :: OSI Approved :: MIT License
Classifier: Operating System :: OS Independent
Classifier: Programming Language :: Python
Classifier: Programming Language :: Python :: 2
Classifier: Programming Language :: Python :: 3
Classifier: Topic :: Multimedia :: Graphics :: Editors :: Vector-Based
Classifier: Topic :: Software Development :: Libraries :: Python Modules
Requires-Dist: pyclipper (>=1.0.5)
Requires-Dist: fonttools (>=3.32.0)
